revolve2/modular_robot_physical/__init__.py
revolve2/modular_robot_physical/_bin/__init__.py
revolve2/modular_robot_physical/_bin/robot_daemon.py
revolve2/modular_robot_physical/_config.py
revolve2/modular_robot_physical/_hardware_type.py
revolve2/modular_robot_physical/_protocol_version.py
revolve2/modular_robot_physical/_standard_port.py
revolve2/modular_robot_physical/_uuid_key.py
revolve2/modular_robot_physical/physical_interfaces/__init__.py
revolve2/modular_robot_physical/physical_interfaces/_get_interface.py
revolve2/modular_robot_physical/physical_interfaces/_physical_interface.py
revolve2/modular_robot_physical/physical_interfaces/v1/__init__.py
revolve2/modular_robot_physical/physical_interfaces/v1/_v1_physical_interface.py
revolve2/modular_robot_physical/physical_interfaces/v2/__init__.py
revolve2/modular_robot_physical/physical_interfaces/v2/_v2_physical_interface.py
revolve2/modular_robot_physical/remote/__init__.py
revolve2/modular_robot_physical/remote/_active_hinge_sensor_state_impl.py
revolve2/modular_robot_physical/remote/_camera_sensor_state_impl.py
revolve2/modular_robot_physical/remote/_imu_sensor_state_impl.py
revolve2/modular_robot_physical/remote/_modular_robot_control_interface_impl.py
revolve2/modular_robot_physical/remote/_modular_robot_sensor_state_impl_v1.py
revolve2/modular_robot_physical/remote/_modular_robot_sensor_state_impl_v2.py
revolve2/modular_robot_physical/remote/_remote.py
revolve2/modular_robot_physical/remote/_test_physical_robot.py
revolve2/modular_robot_physical/robot_daemon/__init__.py
revolve2/modular_robot_physical/robot_daemon/_robo_server_impl.py
revolve2/modular_robot_physical/robot_daemon/_robot_daemon.py
revolve2/modular_robot_physical/robot_daemon_api/__init__.py
revolve2/modular_robot_physical/robot_daemon_api/_generate_stubs.sh
revolve2/modular_robot_physical/robot_daemon_api/robot_daemon_protocol.capnp
revolve2/modular_robot_physical/robot_daemon_api/robot_daemon_protocol_capnp.py
revolve2_modular_robot_physical-1.2.4.dist-info/METADATA
revolve2_modular_robot_physical-1.2.4.dist-info/WHEEL
revolve2_modular_robot_physical-1.2.4.dist-info/RECORD
