Metadata-Version: 2.3
Name: revolve2-modular-robot-physical
Version: 1.2.4
Summary: Revolve2: Everything for physical modular robot control. This package is intended to be installed on the modular robot hardware.
Author: Aart Stuurman
Author-email: aartstuurman@hotmail.com
Requires-Python: >=3.10,<3.12
Classifier: Development Status :: 5 - Production/Stable
Classifier: Intended Audience :: Science/Research
Classifier: License :: OSI Approved :: GNU Lesser General Public License v3 (LGPLv3)
Classifier: Operating System :: OS Independent
Classifier: Programming Language :: Python :: 3
Classifier: Programming Language :: Python :: 3.10
Classifier: Programming Language :: Python :: 3.11
Classifier: Topic :: Scientific/Engineering
Classifier: Typing :: Typed
Provides-Extra: botv1
Provides-Extra: botv2
Provides-Extra: dev
Provides-Extra: remote
Requires-Dist: opencv-python (>=4.10.0.84,<5.0.0.0)
Requires-Dist: pigpio (>=1.78,<2.0) ; extra == "botv1" or extra == "dev"
Requires-Dist: pycapnp (>=2.0.0b2,<3.0.0)
Requires-Dist: pyrr (>=0.10.3,<0.11.0)
Requires-Dist: revolve2-modular-robot (==1.2.4)
Requires-Dist: revolve2-robohat (==0.6.3) ; extra == "botv2" or extra == "dev"
Requires-Dist: rpi-lgpio (==0.5) ; extra == "botv2"
Requires-Dist: typed-argparse (>=0.3.1,<0.4.0)
Project-URL: Repository, https://github.com/ci-group/revolve2
